grahoot_cli/__init__.py
grahoot_cli/grahoot.py
grahoot_cli/helpers.py
grahoot_cli/tls_connection.py
grahootcli-0.2.dist-info/LICENSE
grahootcli-0.2.dist-info/METADATA
grahootcli-0.2.dist-info/WHEEL
grahootcli-0.2.dist-info/entry_points.txt
grahootcli-0.2.dist-info/top_level.txt
grahootcli-0.2.dist-info/RECORD
