Metadata-Version: 2.1
Name: grahootcli
Version: 0.2
Summary: cli client for grahoot
Home-page: https://github.com/fabiancodes/grahoot
Author: Fabian Specht
Author-email: git@fabianspecht.xyz
Classifier: Programming Language :: Python :: 3
Classifier: License :: OSI Approved :: GNU Affero General Public License v3
Classifier: Operating System :: OS Independent
License-File: LICENSE
